flux0_api/__init__.py
flux0_api/agents.py
flux0_api/auth.py
flux0_api/common.py
flux0_api/dependency_injection.py
flux0_api/py.typed
flux0_api/session_service.py
flux0_api/sessions.py
flux0_api/types_agents.py
flux0_api/types_events.py
flux0_api/types_patch.py
flux0_api/types_session.py
flux0_api/types_users.py
flux0_api-0.1.0b3.dist-info/METADATA
flux0_api-0.1.0b3.dist-info/WHEEL
flux0_api-0.1.0b3.dist-info/RECORD
