Metadata-Version: 2.4
Name: flux0-api
Version: 0.1.0b3
Requires-Python: >=3.13
Requires-Dist: fastapi>=0.115.8
Requires-Dist: flux0-core==0.1.0-beta.2
Requires-Dist: flux0-stream==0.1.0-beta.2
Requires-Dist: inflection>=0.5.1
Requires-Dist: lagom>=2.7.5
Requires-Dist: python-dateutil>=2.9.0.post0
Provides-Extra: lagom
Requires-Dist: lagom>=2.7.5; extra == 'lagom'
